aec/__init__.py
aec/main.py
aec/command/__init__.py
aec/command/ami.py
aec/command/compute_optimizer.py
aec/command/ec2.py
aec/command/ssm.py
aec/config-example/__init__.py
aec/config-example/ec2.toml
aec/config-example/userdata/amzn-install-docker.yaml
aec/util/__init__.py
aec/util/cli.py
aec/util/config.py
aec/util/configure.py
aec/util/display.py
aec/util/docgen.py
aec/util/ec2_types.py
aec/util/ec2_util.py
aec/util/errors.py
aec/util/tags.py
aec/util/threads.py
aec_cli-5.0.0.dist-info/licenses/LICENSE
aec_cli-5.0.0.dist-info/METADATA
aec_cli-5.0.0.dist-info/WHEEL
aec_cli-5.0.0.dist-info/entry_points.txt
aec_cli-5.0.0.dist-info/top_level.txt
aec_cli-5.0.0.dist-info/RECORD
