Metadata-Version: 2.4
Name: aec-cli
Version: 5.0.0
Summary: AWS EC2 CLI
License: MIT License
Project-URL: homepage, https://github.com/seek-oss/aec
Keywords: AWS,EC2,command line,cli
Classifier: License :: OSI Approved :: MIT License
Requires-Python: >=3.10
License-File: LICENSE
Requires-Dist: boto3==1.40.69
Requires-Dist: importlib_resources==6.5.2
Requires-Dist: pytoml==0.1.21
Requires-Dist: pytz==2025.2
Requires-Dist: requests==2.32.5
Requires-Dist: rich==14.2.0
Requires-Dist: typing_extensions==4.15.0
Dynamic: license-file
